aiochroma/__init__.py
aiochroma/aiochroma.py
aiochroma/connection.py
aiochroma/const.py
aiochroma/dataclass.py
aiochroma/effects.py
aiochroma/error.py
aiochroma/generators.py
aiochroma-0.3.0.dist-info/licenses/LICENSE
aiochroma-0.3.0.dist-info/licenses/NOTICE
aiochroma-0.3.0.dist-info/METADATA
aiochroma-0.3.0.dist-info/WHEEL
aiochroma-0.3.0.dist-info/top_level.txt
aiochroma-0.3.0.dist-info/RECORD
