Metadata-Version: 2.4
Name: aiochroma
Version: 0.3.0
Summary: API wrapper for communication with Razer Chroma devices
Home-page: https://github.com/Vaskivskyi/aiochroma
Author-email: Yevhenii Vaskivskyi <yevhenii@vaskivskyi.com>
License: Apache-2.0
Project-URL: Source Code, https://github.com/Vaskivskyi/aiochroma
Project-URL: Bug Reports, https://github.com/Vaskivskyi/aiochroma/issues
Classifier: Development Status :: 3 - Alpha
Classifier: Intended Audience :: Developers
Classifier: License :: OSI Approved :: Apache Software License
Classifier: Operating System :: OS Independent
Classifier: Programming Language :: Python :: 3.9
Classifier: Topic :: Software Development :: Libraries
Requires-Python: >=3.9.0
License-File: LICENSE
License-File: NOTICE
Requires-Dist: aiohttp>=3.8.1
Dynamic: license-file
